gau/__init__.py
gau/__version__.py
gau/date_time.py
gau/number.py
gau/security.py
gau/strings.py
gau/transformer.py
gau-0.1.0.dist-info/METADATA
gau-0.1.0.dist-info/WHEEL
gau-0.1.0.dist-info/top_level.txt
gau-0.1.0.dist-info/RECORD
