Metadata-Version: 2.1
Name: gau
Version: 0.1.0
Summary: A Python package
Home-page: https://github.com/ducminhgd/gau
Author: Gia Duong Duc Minh
Author-email: giaduongducminh@gmail.com
Classifier: Programming Language :: Python :: 3
Classifier: License :: OSI Approved :: MIT License
Classifier: Operating System :: OS Independent
Requires-Python: >=3.7
